New/__init__.py
New/outliers.py
visheshv101703622-0.0.2.dist-info/LICENSE.txt
visheshv101703622-0.0.2.dist-info/METADATA
visheshv101703622-0.0.2.dist-info/WHEEL
visheshv101703622-0.0.2.dist-info/entry_points.txt
visheshv101703622-0.0.2.dist-info/top_level.txt
visheshv101703622-0.0.2.dist-info/RECORD
