Metadata-Version: 2.1
Name: visheshv101703622
Version: 0.0.2
Summary: Outliers
Home-page: 
Author: Vishesh Verma
Author-email: visheshv2001@gmail.com
License: UNKNOWN
Platform: UNKNOWN
Classifier: Programming Language :: Python :: 3
Classifier: License :: OSI Approved :: MIT License
Classifier: Operating System :: OS Independent
Requires-Python: >=3.6
Requires-Dist: requests
